its/__init__.py
its/its.py
its-0.0.1.data/scripts/itscli
tests/__init__.py
tests/test_itscli.py
tests/test_sanity.py
its-0.0.1.dist-info/METADATA
its-0.0.1.dist-info/WHEEL
its-0.0.1.dist-info/top_level.txt
its-0.0.1.dist-info/RECORD
