Metadata-Version: 2.1
Name: its
Version: 0.0.1
Summary: An “Issue tracking system” as part of your repository
Home-page: https://github.com/yeger00/its
Author: Avi Yeger
Author-email: yeger00@gmail.com
License: UNKNOWN
Platform: UNKNOWN
